gdriver/__init__.py
gdriver/__init__.pyi
gdriver/cli.py
gdriver/client.py
gdriver/files.py
gdriver/folders.py
gdriver-0.1.1.dist-info/METADATA
gdriver-0.1.1.dist-info/WHEEL
gdriver-0.1.1.dist-info/entry_points.txt
gdriver-0.1.1.dist-info/top_level.txt
gdriver-0.1.1.dist-info/RECORD
