Metadata-Version: 2.1
Name: gdriver
Version: 0.1.1
Summary: Actually usable Google Drive client
Author-email: Marcel Claramunt <marcel@moveread.com>
Project-URL: repo, https://github.com/marciclabas/gdrive.git
Requires-Python: >=3.10
Requires-Dist: pydrive
